roomie_bot/__init__.py
roomie_bot/__main__.py
roomie_bot/api_rest/__init__.py
roomie_bot/api_rest/server.py
roomie_bot/database/__init__.py
roomie_bot/database/database.py
roomie_bot/expenses/__init__.py
roomie_bot/expenses/expenses.py
roomie_bot-0.1.1.dist-info/entry_points.txt
roomie_bot-0.1.1.dist-info/LICENSE
roomie_bot-0.1.1.dist-info/WHEEL
roomie_bot-0.1.1.dist-info/METADATA
roomie_bot-0.1.1.dist-info/RECORD
