Metadata-Version: 2.1
Name: roomie-bot
Version: 0.1.1
Summary: Telegram bot with utilities for roommates
License: GPL-3.0-only
Author: Dipzza
Author-email: dipzza@protonmail.ch
Requires-Python: >=3.7,<4.0
Classifier: License :: OSI Approved :: GNU General Public License v3 (GPLv3)
Classifier: Programming Language :: Python :: 3
Classifier: Programming Language :: Python :: 3.7
Classifier: Programming Language :: Python :: 3.8
Classifier: Programming Language :: Python :: 3.9
Requires-Dist: flask (>=1.1.2,<2.0.0)
Requires-Dist: python-telegram-bot (>=12.8,<13.0)
